setup.py
hoiio/__init__.py
hoiio/exceptions.py
hoiio/rest/__init__.py
hoiio/rest/resources/__init__.py
hoiio/rest/resources/account.py
hoiio/rest/resources/ivr.py
hoiio/rest/resources/number.py
hoiio/rest/resources/sms.py
hoiio/rest/resources/voice.py
python_hoiio.egg-info/PKG-INFO
python_hoiio.egg-info/SOURCES.txt
python_hoiio.egg-info/dependency_links.txt
python_hoiio.egg-info/requires.txt
python_hoiio.egg-info/top_level.txt