Metadata-Version: 1.0
Name: python-hoiio
Version: 0.1
Summary: A python module for Hoiio REST API
Home-page: https://github.com/mickeyckm/python-hoiio
Author: Mickey Cheong
Author-email: mickeyckm@gmail.com
License: UNKNOWN
Platform: UNKNOWN
Classifier: Programming Language :: Python :: 2
